pysfsymbols/__init__.py
pysfsymbols/sf_symbols.py
pysfsymbols/sf_symbols_conversion_table.json
pysfsymbols-0.1.0.dist-info/METADATA
pysfsymbols-0.1.0.dist-info/WHEEL
pysfsymbols-0.1.0.dist-info/RECORD
