Metadata-Version: 2.4
Name: PySFSymbols
Version: 0.1.0
Summary: A Python package for working with SF Symbols within PyQt.
Project-URL: Homepage, https://github.com/th0mcumm1ngs/PySFSymbols
Project-URL: Documentation, https://github.com/th0mcumm1ngs/PySFSymbols#readme
Project-URL: Issues, https://github.com/th0mcumm1ngs/PySFSymbols/issues
Author-email: Thom Cummings <thom-cummings@outlook.com>
License-Expression: MIT
Classifier: Operating System :: OS Independent
Classifier: Programming Language :: Python :: 3
Requires-Python: >=3.9
